ACKNOWLEDGEMENTS.txt
CONTRIBUTING.rst
CONTRIBUTORS.rst
INSTALL.rst
LICENSE.txt
MANIFEST.in
README.rst
RELEASE.rst
requirements.txt
setup.cfg
setup.py
cynetworkx/__init__.c
cynetworkx/__init__.py
cynetworkx/convert.c
cynetworkx/convert.py
cynetworkx/convert_matrix.c
cynetworkx/convert_matrix.py
cynetworkx/exception.c
cynetworkx/exception.py
cynetworkx/relabel.c
cynetworkx/relabel.py
cynetworkx/release.py
cynetworkx/version.py
cynetworkx.egg-info/PKG-INFO
cynetworkx.egg-info/SOURCES.txt
cynetworkx.egg-info/dependency_links.txt
cynetworkx.egg-info/not-zip-safe
cynetworkx.egg-info/requires.txt
cynetworkx.egg-info/top_level.txt
cynetworkx/algorithms/__init__.c
cynetworkx/algorithms/__init__.py
cynetworkx/algorithms/boundary.c
cynetworkx/algorithms/boundary.py
cynetworkx/algorithms/bridges.c
cynetworkx/algorithms/bridges.py
cynetworkx/algorithms/chains.c
cynetworkx/algorithms/chains.py
cynetworkx/algorithms/chordal.c
cynetworkx/algorithms/chordal.py
cynetworkx/algorithms/clique.c
cynetworkx/algorithms/clique.py
cynetworkx/algorithms/cluster.c
cynetworkx/algorithms/cluster.py
cynetworkx/algorithms/communicability_alg.c
cynetworkx/algorithms/communicability_alg.py
cynetworkx/algorithms/core.c
cynetworkx/algorithms/core.py
cynetworkx/algorithms/covering.c
cynetworkx/algorithms/covering.py
cynetworkx/algorithms/cuts.c
cynetworkx/algorithms/cuts.py
cynetworkx/algorithms/cycles.c
cynetworkx/algorithms/cycles.py
cynetworkx/algorithms/dag.c
cynetworkx/algorithms/dag.py
cynetworkx/algorithms/distance_measures.c
cynetworkx/algorithms/distance_measures.py
cynetworkx/algorithms/distance_regular.c
cynetworkx/algorithms/distance_regular.py
cynetworkx/algorithms/dominance.c
cynetworkx/algorithms/dominance.py
cynetworkx/algorithms/dominating.c
cynetworkx/algorithms/dominating.py
cynetworkx/algorithms/efficiency.c
cynetworkx/algorithms/efficiency.py
cynetworkx/algorithms/euler.c
cynetworkx/algorithms/euler.py
cynetworkx/algorithms/graphical.c
cynetworkx/algorithms/graphical.py
cynetworkx/algorithms/hierarchy.c
cynetworkx/algorithms/hierarchy.py
cynetworkx/algorithms/hybrid.c
cynetworkx/algorithms/hybrid.py
cynetworkx/algorithms/isolate.c
cynetworkx/algorithms/isolate.py
